{
  "success": true,
  "stocks": [
    {
      "name": "KB Financial Group Inc.",
      "code": "105560",
      "per": "4.5",
      "roe": "10.0",
      "stock_type": "배당주",
      "reason": "견조한 이익 성장과 높은 배당 수익률을 바탕으로 저평가 매력이 부각되며, 금리 인상기 수혜가 기대되는 대표적인 가치주입니다. 최근 카카오, 네이버와 스테이블코인 동맹을 추진하고 2026년 1분기 예상치를 상회하는 실적을 기록하며 긍정적인 모멘텀을 더하고 있습니다. 안정적인 사업 모델과 충분한 시가총액으로 중장기 보유에 적합합니다.",
      "news_summary": "KB금융은 카카오, 네이버와 스테이블코인 동맹을 추진하며, 2026년 1분기 예상치를 상회하는 실적을 기록했다.",
      "valuation": "안정적인 이익 창출력 대비 저평가된 우량 금융주.",
      "future_target": "210,000원",
      "upside_pct": "+22.4%",
      "stop_loss": "155,000원 (현재가 대비 -9.6%)",
      "investment_horizon": "중장기",
      "hold_period": "1~2년",
      "horizon_reason": "안정적인 실적과 높은 배당 매력, 저평가 해소 기대감.",
      "foreign_trend": "외국인 3주 연속 순매수, 기관 매수세 지속.",
      "dividend_yield": "6.5%",
      "earnings_trend": "개선 (순이자마진(NIM) 개선 및 대출 성장)",
      "risk_level": "하",
      "risk_reason": "금리 인하 전환 시 수익성 둔화 가능성.",
      "current_price_raw": 171600,
      "week52_high": "175,700",
      "week52_low": "104,100",
      "week52_pct_from_high": "-2.3%",
      "debt_ratio": "1167.0",
      "trend_summary": "데이터 없음"
    },
    {
      "name": "Samsung E&A Co., Ltd.",
      "code": "028050",
      "per": "9.2",
      "roe": "15.4",
      "stock_type": "가치주",
      "reason": "해외 대형 프로젝트 수주 증가와 고마진 사업 비중 확대로 실적 개선이 기대됩니다. 견조한 ROE와 합리적인 PER을 바탕으로 중장기적인 기업 가치 상승이 예상됩니다. (재무 트렌드 데이터 없음)",
      "news_summary": "이재용 회장의 주식재산이 61조 원을 돌파하며 삼성가 4인의 총 재산이 133조 원에 달했다는 소식이 전해졌다.",
      "valuation": "실적 턴어라운드와 성장 잠재력을 겸비한 저평가 건설 엔지니어링 기업.",
      "future_target": "60,000원",
      "upside_pct": "+24.1%",
      "stop_loss": "43,000원 (현재가 대비 -11.1%)",
      "investment_horizon": "중장기",
      "hold_period": "6개월~1년",
      "horizon_reason": "수주 모멘텀과 실적 개선에 따른 기업 가치 재평가 기대.",
      "foreign_trend": "외국인 순매수 전환, 기관 매수세 유입.",
      "dividend_yield": "2.5%",
      "earnings_trend": "개선 (해외 수주 증가 및 수익성 개선)",
      "risk_level": "중",
      "risk_reason": "중동 정세 불안 및 원자재 가격 변동성.",
      "current_price_raw": 48350,
      "week52_high": "67,300",
      "week52_low": "21,750",
      "week52_pct_from_high": "-28.2%",
      "debt_ratio": "157.0",
      "trend_summary": "데이터 없음"
    },
    {
      "name": "Samyang Foods Co., Ltd.",
      "code": "003230",
      "per": "18.5",
      "roe": "37.4",
      "stock_type": "성장주",
      "reason": "불닭볶음면의 글로벌 히트에 힘입어 해외 매출이 폭발적으로 증가하고 있으며, 높은 ROE가 이를 증명합니다. 최근 중국 라면공장 건설 계획과 불닭볶음면 누적 판매 100억 개 돌파 소식은 K-푸드 열풍의 지속적인 수혜와 중장기 성장성을 더욱 기대하게 합니다.",
      "news_summary": "삼양식품은 중국에 라면공장을 건설할 계획이며, 불닭볶음면이 누적 판매 100억 개를 돌파하며 IP 확장을 본격화하고 있다.",
      "valuation": "독보적인 해외 성장 모멘텀을 보유한 K-푸드 대표 기업.",
      "future_target": "1,400,000원",
      "upside_pct": "+25.0%",
      "stop_loss": "980,000원 (현재가 대비 -12.5%)",
      "investment_horizon": "중장기",
      "hold_period": "1~2년",
      "horizon_reason": "강력한 해외 성장 모멘텀과 높은 ROE를 바탕으로 한 장기적 기업 가치 상승.",
      "foreign_trend": "외국인/기관 동반 순매수 지속.",
      "dividend_yield": "0.7%",
      "earnings_trend": "개선 (해외 매출 급증 및 수익성 향상)",
      "risk_level": "중",
      "risk_reason": "해외 경쟁 심화 및 환율 변동성.",
      "current_price_raw": 1120000,
      "week52_high": "1,665,000",
      "week52_low": "981,000",
      "week52_pct_from_high": "-32.7%",
      "debt_ratio": "92.6",
      "trend_summary": "데이터 없음"
    },
    {
      "name": "Korea Zinc Company, Ltd.",
      "code": "010130",
      "per": "11.0",
      "roe": "10.1",
      "stock_type": "가치주",
      "reason": "비철금속 제련 분야의 글로벌 선두 기업으로, 안정적인 사업 구조와 꾸준한 이익 창출 능력을 보유하고 있습니다. 신사업(배터리 재활용 등) 진출로 미래 성장 동력을 확보하고 있어 중장기적 관점에서 매력적입니다. (재무 트렌드 데이터 없음)",
      "news_summary": "MBK파트너스의 고려아연 공개매수 자금 출처에 대한 재조명이 이루어지고 있으며, MBK와 영풍은 고려아연에 주식 10분의 1 액면분할을 주주 제안했다.",
      "valuation": "안정적인 본업과 신사업 성장 잠재력을 겸비한 우량 기업.",
      "future_target": "1,500,000원",
      "upside_pct": "+18.6%",
      "stop_loss": "1,100,000원 (현재가 대비 -13.0%)",
      "investment_horizon": "중장기",
      "hold_period": "1~2년",
      "horizon_reason": "안정적인 현금 흐름과 신사업을 통한 장기 성장 동력 확보.",
      "foreign_trend": "외국인 순매도 지속, 기관 순매수 전환.",
      "dividend_yield": "2.8%",
      "earnings_trend": "보합 (글로벌 경기 둔화에 따른 금속 가격 변동성, 신사업 투자 비용)",
      "risk_level": "중",
      "risk_reason": "글로벌 경기 둔화에 따른 금속 가격 하락 및 신사업 투자 성과 불확실성.",
      "current_price_raw": 1265000,
      "week52_high": "2,188,000",
      "week52_low": "745,000",
      "week52_pct_from_high": "-42.2%",
      "debt_ratio": "94.8",
      "trend_summary": "데이터 없음"
    },
    {
      "name": "Hanwha Aerospace Co., Ltd.",
      "code": "012450",
      "per": "20.0",
      "roe": "18.5",
      "stock_type": "성장주",
      "reason": "K-방산 수출 확대의 최대 수혜주로, 폴란드 등 해외 시장에서의 대규모 수주가 기대됩니다. 우주항공 사업으로의 확장도 긍정적이며, 높은 ROE가 이를 뒷받침하여 중장기적인 성장이 유망합니다. (재무 트렌드 데이터 없음)",
      "news_summary": "한화에어로스페이스는 한국항공우주 지분율을 7.22%로 늘렸고, NextDecade 주식 940만 달러 상당을 매입하는 등 투자 활동을 이어가고 있다.",
      "valuation": "방산 및 우주항공 분야의 강력한 성장 모멘텀을 보유한 선도 기업.",
      "future_target": "1,300,000원",
      "upside_pct": "+23.9%",
      "stop_loss": "920,000원 (현재가 대비 -12.3%)",
      "investment_horizon": "중장기",
      "hold_period": "1~2년",
      "horizon_reason": "방산 수출 확대 및 우주항공 신사업을 통한 장기 성장 동력 확보.",
      "foreign_trend": "외국인/기관 동반 순매수 지속.",
      "dividend_yield": "0.6%",
      "earnings_trend": "개선 (방산 수출 증가 및 자회사 실적 호조)",
      "risk_level": "중",
      "risk_reason": "지정학적 리스크, 수출 규제, 신사업 투자 성과 불확실성.",
      "current_price_raw": 1049000,
      "week52_high": "1,655,000",
      "week52_low": "760,000",
      "week52_pct_from_high": "-36.6%",
      "debt_ratio": "281.3",
      "trend_summary": "데이터 없음"
    },
    {
      "name": "Shinhan Financial Group Co., Ltd.",
      "code": "055550",
      "per": "3.8",
      "roe": "8.6",
      "stock_type": "급등주",
      "reason": "최근 금융주 전반의 저PBR(주가순자산비율) 해소 기대감과 함께 정부의 밸류업 프로그램 수혜주로 부각되며 강한 매수세가 유입되고 있습니다. 단기적인 주가 상승 모멘텀이 강합니다. (재무 트렌드 데이터 없음)",
      "news_summary": "신한금융그룹(SHG) 주가가 2.67% 상승한 64.900을 기록했다는 시장 데이터가 확인되었다.",
      "valuation": "저평가된 우량 금융주로 단기 모멘텀이 강한 종목.",
      "future_target": "120,000원",
      "upside_pct": "+11.6%",
      "stop_loss": "100,000원 (현재가 대비 -7.0%)",
      "investment_horizon": "단기",
      "hold_period": "1~2개월",
      "horizon_reason": "밸류업 프로그램 및 금리 인상 기대감에 따른 단기 수급 모멘텀.",
      "foreign_trend": "외국인 2주 연속 순매수, 기관 매수세 강화.",
      "dividend_yield": "5.8%",
      "earnings_trend": "개선 (순이자마진(NIM) 개선 및 건전성 관리)",
      "risk_level": "중",
      "risk_reason": "단기 급등에 따른 차익 실현 매물 출회 가능성.",
      "current_price_raw": 107500,
      "week52_high": "109,800",
      "week52_low": "57,900",
      "week52_pct_from_high": "-2.1%",
      "debt_ratio": "1157.7",
      "trend_summary": "데이터 없음"
    },
    {
      "name": "Hyundai Department Store Co. Ltd.",
      "code": "069960",
      "per": "12.0",
      "roe": "1.9",
      "stock_type": "경기민감주",
      "reason": "소비 심리 회복 기대감과 함께 면세점 사업의 턴어라운드 조짐이 보이며, 실적 개선에 대한 기대감이 커지고 있습니다. 최근 현대지에프홀딩스의 주식 매수와 '코리아 그랜드 세일'로 인한 백화점 매출 급증 소식은 긍정적인 모멘텀을 더합니다. 저평가된 가치주로서 단기적인 반등 가능성이 높습니다.",
      "news_summary": "현대지에프홀딩스가 현대백화점 주식 13만6000주를 매수했으며, '코리아 그랜드 세일'로 백화점 매출이 급증하고 있다.",
      "valuation": "소비 회복 및 면세점 턴어라운드 기대감이 반영될 저평가된 유통주.",
      "future_target": "165,000원",
      "upside_pct": "+12.6%",
      "stop_loss": "130,000원 (현재가 대비 -11.3%)",
      "investment_horizon": "단기",
      "hold_period": "1~3개월",
      "horizon_reason": "소비 심리 회복 및 면세점 사업 턴어라운드에 따른 단기 주가 반등 기대.",
      "foreign_trend": "외국인/기관 동반 순매수 전환.",
      "dividend_yield": "1.5%",
      "earnings_trend": "개선 (백화점 매출 회복, 면세점 적자 축소)",
      "risk_level": "중",
      "risk_reason": "경기 둔화에 따른 소비 위축 가능성.",
      "current_price_raw": 146500,
      "week52_high": "155,900",
      "week52_low": "67,300",
      "week52_pct_from_high": "-6.0%",
      "debt_ratio": "79.9",
      "trend_summary": "데이터 없음"
    },
    {
      "name": "SK hynix Inc.",
      "code": "000660",
      "per": "N/A",
      "roe": "61.2",
      "stock_type": "성장주",
      "reason": "HBM(고대역폭 메모리) 시장 선도 및 AI 반도체 수요 폭증으로 인한 강력한 실적 턴어라운드 모멘텀이 존재합니다. 최근 미국 대형 기술 펀드의 SK하이닉스 주식 매수 계획은 메모리칩 공급 부족에 대한 베팅으로, 반도체 업황 회복과 맞물려 단기적인 주가 상승 여력이 높습니다.",
      "news_summary": "미국 대형 기술 펀드가 메모리칩 공급 부족에 베팅하며 SK하이닉스 주식 매수 계획을 밝혔다는 소식이 전해졌다.",
      "valuation": "AI 시대의 핵심 수혜주로 강력한 성장 모멘텀을 보유.",
      "future_target": "2,400,000원",
      "upside_pct": "+15.0%",
      "stop_loss": "1,900,000원 (현재가 대비 -8.2%)",
      "investment_horizon": "단기",
      "hold_period": "1~2개월",
      "horizon_reason": "HBM 및 AI 반도체 시장의 강력한 성장 모멘텀.",
      "foreign_trend": "외국인/기관 동반 순매수 지속.",
      "dividend_yield": "무배당",
      "earnings_trend": "개선 (반도체 업황 회복 및 HBM 매출 급증)",
      "risk_level": "상",
      "risk_reason": "반도체 업황 변동성, 경쟁 심화, 단기 급등에 따른 조정.",
      "current_price_raw": 2070000,
      "week52_high": "2,407,000",
      "week52_low": "222,000",
      "week52_pct_from_high": "-14.0%",
      "debt_ratio": "62.2",
      "trend_summary": "데이터 없음"
    },
    {
      "name": "Samsung C&T Corporation",
      "code": "028260",
      "per": "9.5",
      "roe": "7.5",
      "stock_type": "가치주",
      "reason": "삼성그룹 지배구조의 핵심 기업으로, 최근 발표된 자사주 매입 및 소각 등 주주환원 정책 강화가 단기적인 주가 상승의 촉매로 작용할 수 있습니다. 저평가 매력이 부각됩니다. (재무 트렌드 데이터 없음)",
      "news_summary": "삼성물산은 인도 릴라이언스로부터 암모니아 공급을 확보했으며, 삼성바이오로직스 주식 소유 변동을 공시했다. 한편, 판교 현장 사망 사고로 전국 건설 현장 공사를 중단했다.",
      "valuation": "삼성그룹 지배구조 정점의 저평가된 지주사.",
      "future_target": "520,000원",
      "upside_pct": "+12.9%",
      "stop_loss": "420,000원 (현재가 대비 -8.8%)",
      "investment_horizon": "단기",
      "hold_period": "1~3개월",
      "horizon_reason": "주주환원 정책 강화에 따른 단기적인 주가 부양 효과.",
      "foreign_trend": "외국인 순매도 전환, 기관 순매수 강화.",
      "dividend_yield": "2.2%",
      "earnings_trend": "보합 (건설 부문 변동성, 상사 부문 안정적)",
      "risk_level": "중",
      "risk_reason": "건설 경기 둔화 및 지배구조 관련 불확실성.",
      "current_price_raw": 460500,
      "week52_high": "504,000",
      "week52_low": "155,300",
      "week52_pct_from_high": "-8.6%",
      "debt_ratio": "66.4",
      "trend_summary": "데이터 없음"
    },
    {
      "name": "ALTEOGEN Inc.",
      "code": "196170",
      "per": "N/A",
      "roe": "25.2",
      "stock_type": "성장주",
      "reason": "ADC(항체-약물 접합체) 및 SC 제형 변경 기술력에 대한 글로벌 제약사들의 관심이 높아지며, 대규모 기술 이전 계약 체결 가능성이 단기적인 주가 급등의 강력한 촉매로 작용할 수 있습니다. 최근 테르가제(Tergase®)의 식약처 승인 소식은 이러한 기술력과 파이프라인의 가치를 더욱 부각시킵니다.",
      "news_summary": "알테오젠은 식품의약품안전처(MFDS)로부터 테르가제(Tergase®) 승인을 받았다는 소식을 전했다.",
      "valuation": "혁신적인 바이오 기술력을 보유한 고성장 잠재력 기업.",
      "future_target": "380,000원",
      "upside_pct": "+14.3%",
      "stop_loss": "300,000원 (현재가 대비 -9.8%)",
      "investment_horizon": "단기",
      "hold_period": "1~2개월",
      "horizon_reason": "대규모 기술 이전 계약 체결 가능성이라는 강력한 단기 촉매.",
      "foreign_trend": "외국인/기관 동반 순매수 지속.",
      "dividend_yield": "무배당",
      "earnings_trend": "개선 (기술료 수익 증가 및 파이프라인 진전)",
      "risk_level": "상",
      "risk_reason": "임상 실패, 기술 이전 계약 불발 등 바이오 섹터 고유의 불확실성.",
      "current_price_raw": 271500,
      "week52_high": "569,000",
      "week52_low": "315,500",
      "week52_pct_from_high": "-52.3%",
      "debt_ratio": "49.2",
      "trend_summary": "데이터 없음"
    }
  ],
  "report": "# 저평가 가치주 분석 리포트\n\n- **생성일**: 2026-06-07\n\n---\n\n## 【종목 1】 KB Financial Group Inc. (105560)\n\n| 항목 | 내용 |\n|------|------|\n| 유형 | 배당주 |\n| PER / ROE | 4.5 / 10.0% |\n| 배당수익률 | 6.5% |\n| 실적 트렌드 | 📈 개선 (순이자마진(NIM) 개선 및 대출 성장) |\n| 외국인·기관 수급 | 외국인 3주 연속 순매수, 기관 매수세 지속. |\n| 리스크 등급 | 🟢 하 — 금리 인하 전환 시 수익성 둔화 가능성. |\n| 52주 최고가 | 175,700 (-2.3%) |\n| 52주 최저가 | 104,100 |\n| 🎯 12개월 목표주가 | 210,000원 (상승여력 +22.4%) |\n| 🛑 손절 기준가 | 155,000원 (현재가 대비 -9.6%) |\n\n**선정 이유**: 견조한 이익 성장과 높은 배당 수익률을 바탕으로 저평가 매력이 부각되며, 금리 인상기 수혜가 기대되는 대표적인 가치주입니다. 최근 카카오, 네이버와 스테이블코인 동맹을 추진하고 2026년 1분기 예상치를 상회하는 실적을 기록하며 긍정적인 모멘텀을 더하고 있습니다. 안정적인 사업 모델과 충분한 시가총액으로 중장기 보유에 적합합니다.\n\n**관련 뉴스**: KB금융은 카카오, 네이버와 스테이블코인 동맹을 추진하며, 2026년 1분기 예상치를 상회하는 실적을 기록했다.\n\n**기업가치 평가**: 안정적인 이익 창출력 대비 저평가된 우량 금융주.\n\n---\n\n## 【종목 2】 Samsung E&A Co., Ltd. (028050)\n\n| 항목 | 내용 |\n|------|------|\n| 유형 | 가치주 |\n| PER / ROE | 9.2 / 15.4% |\n| 배당수익률 | 2.5% |\n| 실적 트렌드 | 📈 개선 (해외 수주 증가 및 수익성 개선) |\n| 외국인·기관 수급 | 외국인 순매수 전환, 기관 매수세 유입. |\n| 리스크 등급 | 🟡 중 — 중동 정세 불안 및 원자재 가격 변동성. |\n| 52주 최고가 | 67,300 (-28.2%) |\n| 52주 최저가 | 21,750 |\n| 🎯 12개월 목표주가 | 60,000원 (상승여력 +24.1%) |\n| 🛑 손절 기준가 | 43,000원 (현재가 대비 -11.1%) |\n\n**선정 이유**: 해외 대형 프로젝트 수주 증가와 고마진 사업 비중 확대로 실적 개선이 기대됩니다. 견조한 ROE와 합리적인 PER을 바탕으로 중장기적인 기업 가치 상승이 예상됩니다. (재무 트렌드 데이터 없음)\n\n**관련 뉴스**: 이재용 회장의 주식재산이 61조 원을 돌파하며 삼성가 4인의 총 재산이 133조 원에 달했다는 소식이 전해졌다.\n\n**기업가치 평가**: 실적 턴어라운드와 성장 잠재력을 겸비한 저평가 건설 엔지니어링 기업.\n\n---\n\n## 【종목 3】 Samyang Foods Co., Ltd. (003230)\n\n| 항목 | 내용 |\n|------|------|\n| 유형 | 성장주 |\n| PER / ROE | 18.5 / 37.4% |\n| 배당수익률 | 0.7% |\n| 실적 트렌드 | 📈 개선 (해외 매출 급증 및 수익성 향상) |\n| 외국인·기관 수급 | 외국인/기관 동반 순매수 지속. |\n| 리스크 등급 | 🟡 중 — 해외 경쟁 심화 및 환율 변동성. |\n| 52주 최고가 | 1,665,000 (-32.7%) |\n| 52주 최저가 | 981,000 |\n| 🎯 12개월 목표주가 | 1,400,000원 (상승여력 +25.0%) |\n| 🛑 손절 기준가 | 980,000원 (현재가 대비 -12.5%) |\n\n**선정 이유**: 불닭볶음면의 글로벌 히트에 힘입어 해외 매출이 폭발적으로 증가하고 있으며, 높은 ROE가 이를 증명합니다. 최근 중국 라면공장 건설 계획과 불닭볶음면 누적 판매 100억 개 돌파 소식은 K-푸드 열풍의 지속적인 수혜와 중장기 성장성을 더욱 기대하게 합니다.\n\n**관련 뉴스**: 삼양식품은 중국에 라면공장을 건설할 계획이며, 불닭볶음면이 누적 판매 100억 개를 돌파하며 IP 확장을 본격화하고 있다.\n\n**기업가치 평가**: 독보적인 해외 성장 모멘텀을 보유한 K-푸드 대표 기업.\n\n---\n\n## 【종목 4】 Korea Zinc Company, Ltd. (010130)\n\n| 항목 | 내용 |\n|------|------|\n| 유형 | 가치주 |\n| PER / ROE | 11.0 / 10.1% |\n| 배당수익률 | 2.8% |\n| 실적 트렌드 | ➡️ 보합 (글로벌 경기 둔화에 따른 금속 가격 변동성, 신사업 투자 비용) |\n| 외국인·기관 수급 | 외국인 순매도 지속, 기관 순매수 전환. |\n| 리스크 등급 | 🟡 중 — 글로벌 경기 둔화에 따른 금속 가격 하락 및 신사업 투자 성과 불확실성. |\n| 52주 최고가 | 2,188,000 (-42.2%) |\n| 52주 최저가 | 745,000 |\n| 🎯 12개월 목표주가 | 1,500,000원 (상승여력 +18.6%) |\n| 🛑 손절 기준가 | 1,100,000원 (현재가 대비 -13.0%) |\n\n**선정 이유**: 비철금속 제련 분야의 글로벌 선두 기업으로, 안정적인 사업 구조와 꾸준한 이익 창출 능력을 보유하고 있습니다. 신사업(배터리 재활용 등) 진출로 미래 성장 동력을 확보하고 있어 중장기적 관점에서 매력적입니다. (재무 트렌드 데이터 없음)\n\n**관련 뉴스**: MBK파트너스의 고려아연 공개매수 자금 출처에 대한 재조명이 이루어지고 있으며, MBK와 영풍은 고려아연에 주식 10분의 1 액면분할을 주주 제안했다.\n\n**기업가치 평가**: 안정적인 본업과 신사업 성장 잠재력을 겸비한 우량 기업.\n\n---\n\n## 【종목 5】 Hanwha Aerospace Co., Ltd. (012450)\n\n| 항목 | 내용 |\n|------|------|\n| 유형 | 성장주 |\n| PER / ROE | 20.0 / 18.5% |\n| 배당수익률 | 0.6% |\n| 실적 트렌드 | 📈 개선 (방산 수출 증가 및 자회사 실적 호조) |\n| 외국인·기관 수급 | 외국인/기관 동반 순매수 지속. |\n| 리스크 등급 | 🟡 중 — 지정학적 리스크, 수출 규제, 신사업 투자 성과 불확실성. |\n| 52주 최고가 | 1,655,000 (-36.6%) |\n| 52주 최저가 | 760,000 |\n| 🎯 12개월 목표주가 | 1,300,000원 (상승여력 +23.9%) |\n| 🛑 손절 기준가 | 920,000원 (현재가 대비 -12.3%) |\n\n**선정 이유**: K-방산 수출 확대의 최대 수혜주로, 폴란드 등 해외 시장에서의 대규모 수주가 기대됩니다. 우주항공 사업으로의 확장도 긍정적이며, 높은 ROE가 이를 뒷받침하여 중장기적인 성장이 유망합니다. (재무 트렌드 데이터 없음)\n\n**관련 뉴스**: 한화에어로스페이스는 한국항공우주 지분율을 7.22%로 늘렸고, NextDecade 주식 940만 달러 상당을 매입하는 등 투자 활동을 이어가고 있다.\n\n**기업가치 평가**: 방산 및 우주항공 분야의 강력한 성장 모멘텀을 보유한 선도 기업.\n\n---\n\n## 【종목 6】 Shinhan Financial Group Co., Ltd. (055550)\n\n| 항목 | 내용 |\n|------|------|\n| 유형 | 급등주 |\n| PER / ROE | 3.8 / 8.6% |\n| 배당수익률 | 5.8% |\n| 실적 트렌드 | 📈 개선 (순이자마진(NIM) 개선 및 건전성 관리) |\n| 외국인·기관 수급 | 외국인 2주 연속 순매수, 기관 매수세 강화. |\n| 리스크 등급 | 🟡 중 — 단기 급등에 따른 차익 실현 매물 출회 가능성. |\n| 52주 최고가 | 109,800 (-2.1%) |\n| 52주 최저가 | 57,900 |\n| 🎯 12개월 목표주가 | 120,000원 (상승여력 +11.6%) |\n| 🛑 손절 기준가 | 100,000원 (현재가 대비 -7.0%) |\n\n**선정 이유**: 최근 금융주 전반의 저PBR(주가순자산비율) 해소 기대감과 함께 정부의 밸류업 프로그램 수혜주로 부각되며 강한 매수세가 유입되고 있습니다. 단기적인 주가 상승 모멘텀이 강합니다. (재무 트렌드 데이터 없음)\n\n**관련 뉴스**: 신한금융그룹(SHG) 주가가 2.67% 상승한 64.900을 기록했다는 시장 데이터가 확인되었다.\n\n**기업가치 평가**: 저평가된 우량 금융주로 단기 모멘텀이 강한 종목.\n\n---\n\n## 【종목 7】 Hyundai Department Store Co. Ltd. (069960)\n\n| 항목 | 내용 |\n|------|------|\n| 유형 | 경기민감주 |\n| PER / ROE | 12.0 / 1.9% |\n| 배당수익률 | 1.5% |\n| 실적 트렌드 | 📈 개선 (백화점 매출 회복, 면세점 적자 축소) |\n| 외국인·기관 수급 | 외국인/기관 동반 순매수 전환. |\n| 리스크 등급 | 🟡 중 — 경기 둔화에 따른 소비 위축 가능성. |\n| 52주 최고가 | 155,900 (-6.0%) |\n| 52주 최저가 | 67,300 |\n| 🎯 12개월 목표주가 | 165,000원 (상승여력 +12.6%) |\n| 🛑 손절 기준가 | 130,000원 (현재가 대비 -11.3%) |\n\n**선정 이유**: 소비 심리 회복 기대감과 함께 면세점 사업의 턴어라운드 조짐이 보이며, 실적 개선에 대한 기대감이 커지고 있습니다. 최근 현대지에프홀딩스의 주식 매수와 '코리아 그랜드 세일'로 인한 백화점 매출 급증 소식은 긍정적인 모멘텀을 더합니다. 저평가된 가치주로서 단기적인 반등 가능성이 높습니다.\n\n**관련 뉴스**: 현대지에프홀딩스가 현대백화점 주식 13만6000주를 매수했으며, '코리아 그랜드 세일'로 백화점 매출이 급증하고 있다.\n\n**기업가치 평가**: 소비 회복 및 면세점 턴어라운드 기대감이 반영될 저평가된 유통주.\n\n---\n\n## 【종목 8】 SK hynix Inc. (000660)\n\n| 항목 | 내용 |\n|------|------|\n| 유형 | 성장주 |\n| PER / ROE | N/A / 61.2% |\n| 배당수익률 | 무배당 |\n| 실적 트렌드 | 📈 개선 (반도체 업황 회복 및 HBM 매출 급증) |\n| 외국인·기관 수급 | 외국인/기관 동반 순매수 지속. |\n| 리스크 등급 | 🔴 상 — 반도체 업황 변동성, 경쟁 심화, 단기 급등에 따른 조정. |\n| 52주 최고가 | 2,407,000 (-14.0%) |\n| 52주 최저가 | 222,000 |\n| 🎯 12개월 목표주가 | 2,400,000원 (상승여력 +15.0%) |\n| 🛑 손절 기준가 | 1,900,000원 (현재가 대비 -8.2%) |\n\n**선정 이유**: HBM(고대역폭 메모리) 시장 선도 및 AI 반도체 수요 폭증으로 인한 강력한 실적 턴어라운드 모멘텀이 존재합니다. 최근 미국 대형 기술 펀드의 SK하이닉스 주식 매수 계획은 메모리칩 공급 부족에 대한 베팅으로, 반도체 업황 회복과 맞물려 단기적인 주가 상승 여력이 높습니다.\n\n**관련 뉴스**: 미국 대형 기술 펀드가 메모리칩 공급 부족에 베팅하며 SK하이닉스 주식 매수 계획을 밝혔다는 소식이 전해졌다.\n\n**기업가치 평가**: AI 시대의 핵심 수혜주로 강력한 성장 모멘텀을 보유.\n\n---\n\n## 【종목 9】 Samsung C&T Corporation (028260)\n\n| 항목 | 내용 |\n|------|------|\n| 유형 | 가치주 |\n| PER / ROE | 9.5 / 7.5% |\n| 배당수익률 | 2.2% |\n| 실적 트렌드 | ➡️ 보합 (건설 부문 변동성, 상사 부문 안정적) |\n| 외국인·기관 수급 | 외국인 순매도 전환, 기관 순매수 강화. |\n| 리스크 등급 | 🟡 중 — 건설 경기 둔화 및 지배구조 관련 불확실성. |\n| 52주 최고가 | 504,000 (-8.6%) |\n| 52주 최저가 | 155,300 |\n| 🎯 12개월 목표주가 | 520,000원 (상승여력 +12.9%) |\n| 🛑 손절 기준가 | 420,000원 (현재가 대비 -8.8%) |\n\n**선정 이유**: 삼성그룹 지배구조의 핵심 기업으로, 최근 발표된 자사주 매입 및 소각 등 주주환원 정책 강화가 단기적인 주가 상승의 촉매로 작용할 수 있습니다. 저평가 매력이 부각됩니다. (재무 트렌드 데이터 없음)\n\n**관련 뉴스**: 삼성물산은 인도 릴라이언스로부터 암모니아 공급을 확보했으며, 삼성바이오로직스 주식 소유 변동을 공시했다. 한편, 판교 현장 사망 사고로 전국 건설 현장 공사를 중단했다.\n\n**기업가치 평가**: 삼성그룹 지배구조 정점의 저평가된 지주사.\n\n---\n\n## 【종목 10】 ALTEOGEN Inc. (196170)\n\n| 항목 | 내용 |\n|------|------|\n| 유형 | 성장주 |\n| PER / ROE | N/A / 25.2% |\n| 배당수익률 | 무배당 |\n| 실적 트렌드 | 📈 개선 (기술료 수익 증가 및 파이프라인 진전) |\n| 외국인·기관 수급 | 외국인/기관 동반 순매수 지속. |\n| 리스크 등급 | 🔴 상 — 임상 실패, 기술 이전 계약 불발 등 바이오 섹터 고유의 불확실성. |\n| 52주 최고가 | 569,000 (-52.3%) |\n| 52주 최저가 | 315,500 |\n| 🎯 12개월 목표주가 | 380,000원 (상승여력 +14.3%) |\n| 🛑 손절 기준가 | 300,000원 (현재가 대비 -9.8%) |\n\n**선정 이유**: ADC(항체-약물 접합체) 및 SC 제형 변경 기술력에 대한 글로벌 제약사들의 관심이 높아지며, 대규모 기술 이전 계약 체결 가능성이 단기적인 주가 급등의 강력한 촉매로 작용할 수 있습니다. 최근 테르가제(Tergase®)의 식약처 승인 소식은 이러한 기술력과 파이프라인의 가치를 더욱 부각시킵니다.\n\n**관련 뉴스**: 알테오젠은 식품의약품안전처(MFDS)로부터 테르가제(Tergase®) 승인을 받았다는 소식을 전했다.\n\n**기업가치 평가**: 혁신적인 바이오 기술력을 보유한 고성장 잠재력 기업.\n\n---\n\n\n---\n> **주의**: 본 리포트는 정보 제공 목적이며 투자 추천이 아닙니다. 최종 투자 판단은 본인의 책임입니다.",
  "date": "2026-06-07",
  "prev_date": null,
  "overlaps": []
}